shell_operator/__init__.py
shell_operator/hook.py
shell_operator/kubernetes.py
shell_operator/metrics.py
shell_operator/module.py
shell_operator/storage.py
shell_operator/values.py
shell_operator-0.1.3.dist-info/LICENSE
shell_operator-0.1.3.dist-info/WHEEL
shell_operator-0.1.3.dist-info/METADATA
shell_operator-0.1.3.dist-info/RECORD
