Metadata-Version: 2.1
Name: shell-operator
Version: 0.1.3
Summary: Python SDK for Shell Operator hooks
License: Apache-2.0
Author: Eugene Shevchenko
Author-email: evgeny.shevchenko@flant.com
Requires-Python: >=3.7.2,<4.0.0
Classifier: License :: OSI Approved :: Apache Software License
Classifier: Programming Language :: Python :: 3
Classifier: Programming Language :: Python :: 3.8
Classifier: Programming Language :: Python :: 3.9
Classifier: Programming Language :: Python :: 3.10
Classifier: Programming Language :: Python :: 3.11
Requires-Dist: dictdiffer (>=0.9.0,<0.10.0)
Requires-Dist: dotmap (>=1.3.30,<2.0.0)
